gbayes/__init__.py
gbayes/gbayes.py
gbayes-0.3.0.dist-info/LICENSE
gbayes-0.3.0.dist-info/WHEEL
gbayes-0.3.0.dist-info/METADATA
gbayes-0.3.0.dist-info/RECORD
