Metadata-Version: 2.1
Name: gbayes
Version: 0.3.0
Summary: GBayes: a minimalistic Computational Framework for Generalized Bayesian Inference.
License: MIT
Author: Tomas A Olego
Requires-Python: >=3.9,<4.0
Classifier: License :: OSI Approved :: MIT License
Classifier: Programming Language :: Python :: 3
Classifier: Programming Language :: Python :: 3.10
Classifier: Programming Language :: Python :: 3.9
